README.rst
setup.py
pipefitter/__init__.py
pipefitter/base.py
pipefitter/pipeline.py
pipefitter.egg-info/PKG-INFO
pipefitter.egg-info/SOURCES.txt
pipefitter.egg-info/dependency_links.txt
pipefitter.egg-info/requires.txt
pipefitter.egg-info/top_level.txt
pipefitter.egg-info/zip-safe
pipefitter/backends/__init__.py
pipefitter/backends/cas/__init__.py
pipefitter/backends/cas/utils.py
pipefitter/backends/cas/estimator/__init__.py
pipefitter/backends/cas/estimator/_assess.py
pipefitter/backends/cas/estimator/base.py
pipefitter/backends/cas/estimator/forest.py
pipefitter/backends/cas/estimator/gradient_boosting.py
pipefitter/backends/cas/estimator/neural_net.py
pipefitter/backends/cas/estimator/regression.py
pipefitter/backends/cas/estimator/tree.py
pipefitter/backends/cas/transformer/__init__.py
pipefitter/backends/cas/transformer/binner.py
pipefitter/backends/cas/transformer/imputer.py
pipefitter/backends/cas/transformer/utils.py
pipefitter/backends/sas/__init__.py
pipefitter/backends/sas/utils.py
pipefitter/backends/sas/estimator/__init__.py
pipefitter/backends/sas/estimator/base.py
pipefitter/backends/sas/estimator/forest.py
pipefitter/backends/sas/estimator/gradient_boosting.py
pipefitter/backends/sas/estimator/neural_net.py
pipefitter/backends/sas/estimator/regression.py
pipefitter/backends/sas/estimator/tree.py
pipefitter/backends/sas/transformer/__init__.py
pipefitter/backends/sas/transformer/imputer.py
pipefitter/estimator/__init__.py
pipefitter/estimator/forest.py
pipefitter/estimator/gradient_boosting.py
pipefitter/estimator/neural_net.py
pipefitter/estimator/regression.py
pipefitter/estimator/tree.py
pipefitter/model_selection/__init__.py
pipefitter/model_selection/search.py
pipefitter/tests/__init__.py
pipefitter/tests/test_base.py
pipefitter/tests/test_hyper.py
pipefitter/tests/test_params.py
pipefitter/tests/cas/__init__.py
pipefitter/tests/cas/test_base.py
pipefitter/tests/cas/test_binner.py
pipefitter/tests/cas/test_dtree.py
pipefitter/tests/cas/test_forest.py
pipefitter/tests/cas/test_gbtree.py
pipefitter/tests/cas/test_hyper.py
pipefitter/tests/cas/test_imputer.py
pipefitter/tests/cas/test_nn.py
pipefitter/tests/cas/test_pipeline.py
