Metadata-Version: 1.1
Name: pipefitter
Version: 1.0.0
Summary: SAS Pipefitter
Home-page: http://github.com/sassoftware/python-pipefitter/
Author: SAS
Author-email: Kevin.Smith@sas.com
License: Apache v2.0
Platform: UNKNOWN
Classifier: Development Status :: 5 - Production/Stable
Classifier: Environment :: Console
Classifier: Intended Audience :: Science/Research
Classifier: Programming Language :: Python
Classifier: Programming Language :: Python :: 2
Classifier: Programming Language :: Python :: 3
Classifier: Programming Language :: Python :: 2.7
Classifier: Programming Language :: Python :: 3.4
Classifier: Programming Language :: Python :: 3.5
Classifier: Programming Language :: Python :: 3.6
Classifier: Topic :: Scientific/Engineering
